<?xml version="1.0" encoding="utf-8"?>
<!DOCTYPE hibernate-mapping PUBLIC "-//Hibernate/Hibernate Mapping DTD 3.0//EN"
"http://hibernate.sourceforge.net/hibernate-mapping-3.0.dtd">
<!-- 
    Mapping file autogenerated by MyEclipse Persistence Tools
-->
<hibernate-mapping>
    <class name="com.unieap.pojo.Userrole" table="userrole" catalog="unieap">
        <id name="roleResId" type="java.lang.Long">
            <column name="roleResId" />
            <generator class="assigned" />
        </id>
        <property name="roleId" type="java.lang.Long">
            <column name="roleId" />
        </property>
        <property name="resourceId" type="java.lang.Long">
            <column name="resourceId" precision="16" scale="0" />
        </property>
        <property name="activeFlag" type="java.lang.String">
            <column name="activeFlag" length="1" />
        </property>
        <property name="createDatetime" type="java.lang.String">
            <column name="createDatetime" length="32" />
        </property>
        <property name="modifyDatetime" type="java.lang.String">
            <column name="modifyDatetime" length="32" />
        </property>
        <property name="remark" type="java.lang.String">
            <column name="remark" length="128" />
        </property>
    </class>
</hibernate-mapping>
